py_gitignore_2/__init__.py
py_gitignore_2/gitignore.py
py_gitignore_2/gitignoreBuilder.py
py_gitignore_2/gitignoreMatcher.py
py_gitignore_2/glob.py
py_gitignore_2-0.0.1.dist-info/METADATA
py_gitignore_2-0.0.1.dist-info/WHEEL
py_gitignore_2-0.0.1.dist-info/licenses/LICENSE
py_gitignore_2-0.0.1.dist-info/RECORD
