Metadata-Version: 2.1
Name: py_gitignore_2
Version: 0.0.1
Summary: Python implementation of a gitignore parser and checker
Project-URL: Homepage, https://github.com/thehanimo/py-gitignore
Project-URL: Issues, https://github.com/thehanimo/py-gitignore/issues
Author-email: Hani Mohammed <hani.m17@iiits.in>, Anil Poonai <ap5254@nyu.edu>, Kishore Moorthy <ksm5985@nyu.edu>, Omar Hammami <oh524@nyu.edu>, Sean Balakhanei <sb7671@nyu.edu>
License-File: LICENSE
Classifier: License :: OSI Approved :: MIT License
Classifier: Operating System :: OS Independent
Classifier: Programming Language :: Python :: 3
Requires-Python: >=3.8
